jsfsdb/__init__.py
jsfsdb/__meta__.py
jsfsdb/tests.py
jsfsdb-0.1.2.dist-info/METADATA
jsfsdb-0.1.2.dist-info/WHEEL
jsfsdb-0.1.2.dist-info/top_level.txt
jsfsdb-0.1.2.dist-info/RECORD
