Metadata-Version: 2.1
Name: jsfsdb
Version: 0.1.2
Summary: jsfsdb is a json-on-filesystem database
Home-page: http://jsfsdb.readthedocs.io
Author: Ian Dennis Miller
Author-email: ian@iandennismiller.com
License: MIT
Platform: UNKNOWN
Requires-Dist: jq
